klokke/__init__.py
klokke/decorator.py
klokke/timer.py
klokke-0.1.0.dist-info/LICENSE.md
klokke-0.1.0.dist-info/WHEEL
klokke-0.1.0.dist-info/METADATA
klokke-0.1.0.dist-info/RECORD
