Metadata-Version: 2.1
Name: klokke
Version: 0.1.0
Summary: A small library for high level measurement of code execution time
License: MIT
Author: Magnus Heskestad Waage
Author-email: magnushwaage@gmail.com
Requires-Python: >=3.8,<4.0
Classifier: License :: OSI Approved :: MIT License
Classifier: Programming Language :: Python :: 3
Classifier: Programming Language :: Python :: 3.8
Classifier: Programming Language :: Python :: 3.9
Classifier: Programming Language :: Python :: 3.10
